ezc3d-1.5.19.data/data/CMakeLists.txt
ezc3d-1.5.19.data/data/LICENSE
ezc3d-1.5.19.data/data/environment.yml
ezc3d-1.5.19.data/data/cmake_uninstall.cmake.in
ezc3d-1.5.19.data/data/pyproject.toml
ezc3d-1.5.19.data/data/MANIFEST.in
ezc3d-1.5.19.data/data/README.md
ezc3d-1.5.19.data/data/setup.py
ezc3d-1.5.19.data/data/include/ezc3d/Channel.h
ezc3d-1.5.19.data/data/include/ezc3d/ezc3dConfig.h
ezc3d-1.5.19.data/data/include/ezc3d/Header.h
ezc3d-1.5.19.data/data/include/ezc3d/AnalogsSubframe.h
ezc3d-1.5.19.data/data/include/ezc3d/Point.h
ezc3d-1.5.19.data/data/include/ezc3d/ezc3dNamespace.h
ezc3d-1.5.19.data/data/include/ezc3d/Parameter.h
ezc3d-1.5.19.data/data/include/ezc3d/Data.h
ezc3d-1.5.19.data/data/include/ezc3d/Analogs.h
ezc3d-1.5.19.data/data/include/ezc3d/Frame.h
ezc3d-1.5.19.data/data/include/ezc3d/Rotation.h
ezc3d-1.5.19.data/data/include/ezc3d/DataStartInfo.h
ezc3d-1.5.19.data/data/include/ezc3d/AnalogsInfo.h
ezc3d-1.5.19.data/data/include/ezc3d/RotationsInfo.h
ezc3d-1.5.19.data/data/include/ezc3d/Rotations.h
ezc3d-1.5.19.data/data/include/ezc3d/Parameters.h
ezc3d-1.5.19.data/data/include/ezc3d/Group.h
ezc3d-1.5.19.data/data/include/ezc3d/ezc3d_all.h
ezc3d-1.5.19.data/data/include/ezc3d/RotationsSubframe.h
ezc3d-1.5.19.data/data/include/ezc3d/PointsInfo.h
ezc3d-1.5.19.data/data/include/ezc3d/Points.h
ezc3d-1.5.19.data/data/include/ezc3d/ezc3d.h
ezc3d-1.5.19.data/data/include/ezc3d/math/ezc3dMath.h
ezc3d-1.5.19.data/data/include/ezc3d/math/Matrix44.h
ezc3d-1.5.19.data/data/include/ezc3d/math/Matrix66.h
ezc3d-1.5.19.data/data/include/ezc3d/math/Matrix.h
ezc3d-1.5.19.data/data/include/ezc3d/math/Matrix33.h
ezc3d-1.5.19.data/data/include/ezc3d/math/Vector3d.h
ezc3d-1.5.19.data/data/include/ezc3d/math/Vector6d.h
ezc3d-1.5.19.data/data/include/ezc3d/modules/ForcePlatforms.h
ezc3d-1.5.19.dist-info/RECORD
ezc3d-1.5.19.dist-info/WHEEL
ezc3d-1.5.19.dist-info/top_level.txt
ezc3d-1.5.19.dist-info/METADATA
ezc3d-1.5.19.dist-info/licenses/LICENSE
ezc3d/_ezc3d.so
ezc3d/_version.py
ezc3d/__init__.py
ezc3d/libezc3d.dylib
ezc3d/ezc3d.py
ezc3d/cmake/ezc3d/ezc3dTargets.cmake
