Metadata-Version: 2.4
Name: ezc3d
Version: 1.5.19
Summary: Easy to use C3D reader/writer for C++, Python, and Matlab
Home-page: https://github.com/pyomeca/ezc3d
Author: Michaud, Benjamin, Begon, Mickaël
License: MIT
Project-URL: Homepage, https://github.com/pyomeca/ezc3d
Requires-Python: >=3.10
License-File: LICENSE
Requires-Dist: numpy
Dynamic: home-page
Dynamic: license-file
